[
    {
        "content": "<p>how to build rustc with -Zverbose. I tried <code>RUSTFLAGS=-Zverbose &lt;build cmd&gt;</code> but I get -Z are only allowed on nightly (not surprising I guess). </p>\n<p>When I run x.py --verbose, it seem to be printing info on bootstrapping than running rust with -Zverbose</p>",
        "id": 217241897,
        "sender_full_name": "Aman Arora",
        "timestamp": 1605775896
    },
    {
        "content": "<p>-Z verbose is a rustc flag? Try |<code>RUSTFLAGS_BOOTSTRAP</code></p>",
        "id": 217267634,
        "sender_full_name": "Joshua Nelson",
        "timestamp": 1605792123
    }
]