[
    {
        "content": "<p>Gonna try something new today since after reviewing the agenda it doesn't seem like we have much new to report, lets try doing an async update where we focus on populating the hackmd with notes and updates</p>",
        "id": 249623428,
        "sender_full_name": "Jane Lusby",
        "timestamp": 1629136483
    },
    {
        "content": "<p>Here's this week's agenda: <a href=\"https://hackmd.io/SKyk3AU5QsikPrlUfMP7SA?both\">https://hackmd.io/SKyk3AU5QsikPrlUfMP7SA?both</a></p>",
        "id": 249623518,
        "sender_full_name": "Jane Lusby",
        "timestamp": 1629136538
    },
    {
        "content": "<p>I went ahead and updated most of the <code>A-error-handling</code> section</p>",
        "id": 249623827,
        "sender_full_name": "Jane Lusby",
        "timestamp": 1629136665
    },
    {
        "content": "<p><span aria-label=\"+1\" class=\"emoji emoji-1f44d\" role=\"img\" title=\"+1\">:+1:</span></p>",
        "id": 249624837,
        "sender_full_name": "Charles Ellis O'Riley Jr.",
        "timestamp": 1629137067
    },
    {
        "content": "<p>Great!</p>",
        "id": 249625166,
        "sender_full_name": "Jakub Duchniewicz",
        "timestamp": 1629137246
    },
    {
        "content": "<p>Awesome</p>",
        "id": 251282315,
        "sender_full_name": "Senyo Simpson",
        "timestamp": 1630352149
    }
]