[
    {
        "content": "<p><a href=\"https://github.com/rust-lang/rust/issues/94089\">https://github.com/rust-lang/rust/issues/94089</a> points out that the breadcrumbs at the top of the page are an important navigation element (the way to get to a parent modules), but they aren't styled like links. I think that makes sense, and we should give them the same color that other hyperlinks in the page use.</p>\n<p>Thoughts?</p>",
        "id": 272370825,
        "sender_full_name": "jsha",
        "timestamp": 1645170927
    },
    {
        "content": "<p>I'm not convinced by the argument but I'm waiting a demo to see what it looks like.</p>",
        "id": 272378829,
        "sender_full_name": "GuillaumeGomez",
        "timestamp": 1645176524
    }
]