[
    {
        "content": "<p>I’m not sure where to put this. Is <code>cargo fix</code> supposed to do things for non-edition lints?</p>",
        "id": 254077544,
        "sender_full_name": "Simon Sapin",
        "timestamp": 1632155204
    },
    {
        "content": "<p>In my case, running it prints the same warnings as <code>cargo check</code>, many instances of:</p>\n<div class=\"codehilite\"><pre><span></span><code>warning: associated constant `p1_tracked` should have an upper case name\n  --&gt; hg-core/src/dirstate/entry.rs:29:15\n   |\n29 |         const p1_tracked = 1 &lt;&lt; 1;\n   |               ^^^^^^^^^^ help: convert the identifier to upper case: `P1_TRACKED`\n</code></pre></div>\n<p>… but no source file is changed</p>",
        "id": 254077810,
        "sender_full_name": "Simon Sapin",
        "timestamp": 1632155317
    },
    {
        "content": "<p>Since I have many constant names (copy-pasted from another language) I wouldn’t mind having a tool making them all upper case for me</p>",
        "id": 254077894,
        "sender_full_name": "Simon Sapin",
        "timestamp": 1632155358
    },
    {
        "content": "<p>It automatically fixes only those lints that have suggestions marked as <code>MachineApplicable</code>. <code>non_upper_case_globals</code> for example is only marked as <code>MaybeIncorrect</code>, so it is not automatically fixed. There's an open issue for improving this behaviour <a href=\"https://github.com/rust-lang/rustfix/issues/200\">https://github.com/rust-lang/rustfix/issues/200</a></p>",
        "id": 254080256,
        "sender_full_name": "Giacomo Stevanato",
        "timestamp": 1632156326
    },
    {
        "content": "<p>Do we currently have any machine applicable lints that update all use sites?</p>",
        "id": 254082900,
        "sender_full_name": "Gary Guo",
        "timestamp": 1632157316
    },
    {
        "content": "<p>This looks non-trivial, since it probably needs to consider privacy as well.</p>",
        "id": 254083022,
        "sender_full_name": "Gary Guo",
        "timestamp": 1632157353
    },
    {
        "content": "<p>rust-analyser can rename a symbol and all of its uses</p>",
        "id": 254223215,
        "sender_full_name": "Simon Sapin",
        "timestamp": 1632236996
    },
    {
        "content": "<p>in this case though there weren’t any use yet</p>",
        "id": 254223285,
        "sender_full_name": "Simon Sapin",
        "timestamp": 1632237007
    },
    {
        "content": "<p>but yeah I can see new how applying the suggested change is not easy in the general case</p>",
        "id": 254223354,
        "sender_full_name": "Simon Sapin",
        "timestamp": 1632237038
    }
]