[
    {
        "content": "<p><span class=\"user-mention\" data-user-id=\"116113\">@lqd</span> <a href=\"/user_uploads/4715/pM0KQkrQFgbdqF3vn7cs0ps5/pasted_image.png\" target=\"_blank\" title=\"pasted_image.png\">pasted image</a></p>\n<div class=\"message_inline_image\"><a href=\"/user_uploads/4715/pM0KQkrQFgbdqF3vn7cs0ps5/pasted_image.png\" target=\"_blank\" title=\"pasted image\"><img src=\"/user_uploads/4715/pM0KQkrQFgbdqF3vn7cs0ps5/pasted_image.png\"></a></div>",
        "id": 128678141,
        "sender_full_name": "Jake Goulding",
        "timestamp": 1530045004
    },
    {
        "content": "<p>Need your thinking brain again</p>",
        "id": 128678161,
        "sender_full_name": "Jake Goulding",
        "timestamp": 1530045020
    },
    {
        "content": "<p>this seems familiar, lemme check a couple things; I think it's related to opacity in the button's vicinity</p>",
        "id": 128678213,
        "sender_full_name": "lqd",
        "timestamp": 1530045091
    },
    {
        "content": "<p>to be more precise, that the way I initially did this for the prototype, now makes this opacity bug</p>",
        "id": 128678296,
        "sender_full_name": "lqd",
        "timestamp": 1530045154
    },
    {
        "content": "<p>Oh, I made this from scratch, no \"bug\" ;-)</p>",
        "id": 128678444,
        "sender_full_name": "Jake Goulding",
        "timestamp": 1530045309
    },
    {
        "content": "<p><span class=\"user-mention\" data-user-id=\"116155\">@Jake Goulding</span> do you happen to have a URL I could play with in the browser directly (so that I don't have to update my dev environment; it's ok if you don't, it'll just be slower)</p>",
        "id": 128678449,
        "sender_full_name": "lqd",
        "timestamp": 1530045314
    },
    {
        "content": "<p>oh :)</p>",
        "id": 128678468,
        "sender_full_name": "lqd",
        "timestamp": 1530045335
    },
    {
        "content": "<p>is this the \"rust blue\" btw ?</p>",
        "id": 128678551,
        "sender_full_name": "lqd",
        "timestamp": 1530045387
    },
    {
        "content": "<p><span class=\"user-mention\" data-user-id=\"116113\">@lqd</span> <a href=\"http://69e9a319.ngrok.io/\" target=\"_blank\" title=\"http://69e9a319.ngrok.io/\">http://69e9a319.ngrok.io/</a></p>",
        "id": 128678554,
        "sender_full_name": "Jake Goulding",
        "timestamp": 1530045389
    },
    {
        "content": "<p>awesome thank you</p>",
        "id": 128678565,
        "sender_full_name": "lqd",
        "timestamp": 1530045404
    },
    {
        "content": "<p>FWIW, I get a phishing warning on that; guess people are misusing ngrok :-(</p>",
        "id": 128678592,
        "sender_full_name": "Jake Goulding",
        "timestamp": 1530045431
    },
    {
        "content": "<p>don't type your password into the playground</p>",
        "id": 128678599,
        "sender_full_name": "Jake Goulding",
        "timestamp": 1530045440
    },
    {
        "content": "<p>too late I already input my creditcard to access the 1000 most popular crates</p>",
        "id": 128678617,
        "sender_full_name": "lqd",
        "timestamp": 1530045473
    },
    {
        "content": "<p>there's an idea. Pay by the crate.</p>",
        "id": 128678670,
        "sender_full_name": "Jake Goulding",
        "timestamp": 1530045491
    },
    {
        "content": "<blockquote>\n<p>Find open source crates near ANONYMOUS PROXY</p>\n</blockquote>",
        "id": 128678691,
        "sender_full_name": "Jake Goulding",
        "timestamp": 1530045525
    },
    {
        "content": "<p>VPNs hate him</p>",
        "id": 128678704,
        "sender_full_name": "lqd",
        "timestamp": 1530045542
    },
    {
        "content": "<p>I'm thinking it's be awesome to have an indicator for \"this isn't the default\" in the menu <em>and</em> on each non-default item. That way you will click it and can figure out <em>why</em>.</p>",
        "id": 128678758,
        "sender_full_name": "Jake Goulding",
        "timestamp": 1530045595
    },
    {
        "content": "<p>so something that could be stylistically reused would be ++</p>",
        "id": 128678820,
        "sender_full_name": "Jake Goulding",
        "timestamp": 1530045621
    },
    {
        "content": "<p>good/interesting/tough idea</p>",
        "id": 128678846,
        "sender_full_name": "lqd",
        "timestamp": 1530045655
    },
    {
        "content": "<p>Naturally. Was poking at <a href=\"https://ux.stackexchange.com/questions/35307/how-to-visually-indicate-a-change-in-setting\" target=\"_blank\" title=\"https://ux.stackexchange.com/questions/35307/how-to-visually-indicate-a-change-in-setting\">https://ux.stackexchange.com/questions/35307/how-to-visually-indicate-a-change-in-setting</a> for ideas</p>",
        "id": 128678943,
        "sender_full_name": "Jake Goulding",
        "timestamp": 1530045754
    },
    {
        "content": "<p>thus how I got to the blue w/outline</p>",
        "id": 128678963,
        "sender_full_name": "Jake Goulding",
        "timestamp": 1530045778
    },
    {
        "content": "<p>oh I remember the troubles I was having with this before, doing this outline quickly, in a pseudo element somehow always ended up on top of the ellipsis, even after fighting with z-index and all</p>",
        "id": 128678969,
        "sender_full_name": "lqd",
        "timestamp": 1530045784
    },
    {
        "content": "<p>ha, I cheated and just duplicated the SVG</p>",
        "id": 128679066,
        "sender_full_name": "Jake Goulding",
        "timestamp": 1530045885
    },
    {
        "content": "<p>which was pretty easy</p>",
        "id": 128679072,
        "sender_full_name": "Jake Goulding",
        "timestamp": 1530045901
    },
    {
        "content": "<p>what's the css class you were using in that screenshot btw ?</p>",
        "id": 128679090,
        "sender_full_name": "lqd",
        "timestamp": 1530045942
    },
    {
        "content": "<p>No CSS; If you select 2015/2018 it switches the SVG to one that had an ellipse</p>",
        "id": 128679263,
        "sender_full_name": "Jake Goulding",
        "timestamp": 1530046131
    },
    {
        "content": "<p>I kind of like the rounded rect</p>\n<div class=\"codehilite\"><pre><span></span>&lt;rect x=&quot;1&quot; y=&quot;3&quot; width=&quot;22&quot; height=&quot;18&quot; rx=&quot;3&quot; ry=&quot;3&quot; fill=&quot;#0044FF88&quot; stroke=&quot;#0044FFFF&quot; stroke-width=&quot;2&quot;&gt;&lt;/rect&gt;\n</pre></div>\n\n\n<p><a href=\"/user_uploads/4715/jlUZlh-U65TaA1jotsk-U6cz/pasted_image.png\" target=\"_blank\" title=\"pasted_image.png\">pasted image</a></p>\n<div class=\"message_inline_image\"><a href=\"/user_uploads/4715/jlUZlh-U65TaA1jotsk-U6cz/pasted_image.png\" target=\"_blank\" title=\"pasted image\"><img src=\"/user_uploads/4715/jlUZlh-U65TaA1jotsk-U6cz/pasted_image.png\"></a></div>",
        "id": 128679292,
        "sender_full_name": "Jake Goulding",
        "timestamp": 1530046174
    },
    {
        "content": "<p>this is from the old prototype:</p>",
        "id": 128679379,
        "sender_full_name": "lqd",
        "timestamp": 1530046259
    },
    {
        "content": "<p><a href=\"/user_uploads/4715/USyYT64vXxt_mpnv6k9DJeAV/pasted_image.png\" target=\"_blank\" title=\"pasted_image.png\">pasted image</a></p>\n<div class=\"message_inline_image\"><a href=\"/user_uploads/4715/USyYT64vXxt_mpnv6k9DJeAV/pasted_image.png\" target=\"_blank\" title=\"pasted image\"><img src=\"/user_uploads/4715/USyYT64vXxt_mpnv6k9DJeAV/pasted_image.png\"></a></div>",
        "id": 128679381,
        "sender_full_name": "lqd",
        "timestamp": 1530046261
    },
    {
        "content": "<p>between 0.8 and 1.0 opacity on the parent \"header-button__left-icon\" + #428bca fill (but no stroke)</p>",
        "id": 128679411,
        "sender_full_name": "lqd",
        "timestamp": 1530046315
    },
    {
        "content": "<p>well then. great minds</p>",
        "id": 128679467,
        "sender_full_name": "Jake Goulding",
        "timestamp": 1530046349
    },
    {
        "content": "<p>in a sense, if it were used to highlight in the popover window that \"Edition\" has been changed, the Edition label would kind of look like the boolean toggles from the Config popover</p>",
        "id": 128679499,
        "sender_full_name": "lqd",
        "timestamp": 1530046424
    },
    {
        "content": "<p>true. Maybe just the bold text then...</p>",
        "id": 128679593,
        "sender_full_name": "Jake Goulding",
        "timestamp": 1530046525
    },
    {
        "content": "<p>maybe a similar small rounded rect before the Edition label could call back to it, in addition to a note/aside (like the wasm one, maybe blue if you wanted) explaining why it's changed</p>",
        "id": 128679607,
        "sender_full_name": "lqd",
        "timestamp": 1530046547
    },
    {
        "content": "<p>or indeed just bold/blue like the hover on the other popovers' options</p>",
        "id": 128679658,
        "sender_full_name": "lqd",
        "timestamp": 1530046581
    },
    {
        "content": "<p>I wonder if I should eschew the opacity on the icon CSS and move that to the SVG directly. Otherwise can't really get full control</p>",
        "id": 128679756,
        "sender_full_name": "Jake Goulding",
        "timestamp": 1530046693
    },
    {
        "content": "<p>Since the icons are 50% opacity now</p>",
        "id": 128679768,
        "sender_full_name": "Jake Goulding",
        "timestamp": 1530046707
    },
    {
        "content": "<p>you can move it to the svg's root css for sure here yeah, it'll make things easier</p>",
        "id": 128679792,
        "sender_full_name": "lqd",
        "timestamp": 1530046751
    },
    {
        "content": "<p><a href=\"/user_uploads/4715/nq1WwzKSeFcY8oFMwkcm4IGN/pasted_image.png\" target=\"_blank\" title=\"pasted_image.png\">pasted image</a> 50% of that color looks meh</p>\n<div class=\"message_inline_image\"><a href=\"/user_uploads/4715/nq1WwzKSeFcY8oFMwkcm4IGN/pasted_image.png\" target=\"_blank\" title=\"pasted image\"><img src=\"/user_uploads/4715/nq1WwzKSeFcY8oFMwkcm4IGN/pasted_image.png\"></a></div>",
        "id": 128679865,
        "sender_full_name": "Jake Goulding",
        "timestamp": 1530046812
    },
    {
        "content": "<p>also, zooming in does that whole brain trick where it looks yellow in the dots</p>",
        "id": 128679883,
        "sender_full_name": "Jake Goulding",
        "timestamp": 1530046843
    },
    {
        "content": "<p>0.8 at least I'd think yeah</p>",
        "id": 128679995,
        "sender_full_name": "lqd",
        "timestamp": 1530046998
    },
    {
        "content": "<p>they do look yellow is this a new illusion :)</p>",
        "id": 128680017,
        "sender_full_name": "lqd",
        "timestamp": 1530047031
    },
    {
        "content": "<p><a href=\"/user_uploads/4715/q_gyqyDcl7CaUBF4kPWW57V_/pasted_image.png\" target=\"_blank\" title=\"pasted_image.png\">pasted image</a></p>\n<div class=\"message_inline_image\"><a href=\"/user_uploads/4715/q_gyqyDcl7CaUBF4kPWW57V_/pasted_image.png\" target=\"_blank\" title=\"pasted image\"><img src=\"/user_uploads/4715/q_gyqyDcl7CaUBF4kPWW57V_/pasted_image.png\"></a></div>",
        "id": 128680020,
        "sender_full_name": "lqd",
        "timestamp": 1530047036
    },
    {
        "content": "<p>(+ we can/should have more padding on the sides, 0.25-0.5 ems I'd guess; 3-4px in non-shep units ;)</p>",
        "id": 128680160,
        "sender_full_name": "lqd",
        "timestamp": 1530047163
    },
    {
        "content": "<p>if we used this rounded-rect as a hook \"look at meee\" <a href=\"/user_uploads/4715/CsGtxSDJAPaXkZAAbhjY_Gr7/pasted_image.png\" target=\"_blank\" title=\"pasted_image.png\">pasted image</a></p>\n<div class=\"message_inline_image\"><a href=\"/user_uploads/4715/CsGtxSDJAPaXkZAAbhjY_Gr7/pasted_image.png\" target=\"_blank\" title=\"pasted image\"><img src=\"/user_uploads/4715/CsGtxSDJAPaXkZAAbhjY_Gr7/pasted_image.png\"></a></div>",
        "id": 128680315,
        "sender_full_name": "lqd",
        "timestamp": 1530047390
    },
    {
        "content": "<p>You and your padding</p>",
        "id": 128680549,
        "sender_full_name": "Jake Goulding",
        "timestamp": 1530047654
    },
    {
        "content": "<p>it's the same padding as the config menu</p>",
        "id": 128680560,
        "sender_full_name": "Jake Goulding",
        "timestamp": 1530047680
    },
    {
        "content": "<p>Using the rect before the label means the label will bounce as people change options</p>",
        "id": 128680576,
        "sender_full_name": "Jake Goulding",
        "timestamp": 1530047707
    },
    {
        "content": "<p>could go wild... lemme try a jsbin</p>",
        "id": 128680612,
        "sender_full_name": "Jake Goulding",
        "timestamp": 1530047762
    },
    {
        "content": "<p>true; could go in the margin of after the label ;)</p>",
        "id": 128680672,
        "sender_full_name": "lqd",
        "timestamp": 1530047821
    },
    {
        "content": "<p>(to be clearer I meant padding inside the rounded rect; just a bit more whitespace/bluespace around the ellipsis that's all, the rest of the button is as fine as last time I bothered you about it :)</p>",
        "id": 128680709,
        "sender_full_name": "lqd",
        "timestamp": 1530047871
    },
    {
        "content": "<p>Oh, padding of the button. Could be a wee bit tricky cause the box is butting right up against the icon size at the moment</p>",
        "id": 128680879,
        "sender_full_name": "Jake Goulding",
        "timestamp": 1530048038
    },
    {
        "content": "<p>but probably worth tweaking</p>",
        "id": 128680888,
        "sender_full_name": "Jake Goulding",
        "timestamp": 1530048057
    },
    {
        "content": "<p>at least the bouncing of the Edition label could be animated into a slide, or not be that bad as the popover would still be static — but yeah, true, things would probably still bounce vertically as the aside is shown/hidden depending on the option</p>",
        "id": 128681049,
        "sender_full_name": "lqd",
        "timestamp": 1530048264
    },
    {
        "content": "<p><span class=\"user-mention\" data-user-id=\"116113\">@lqd</span> WDYT about a sliding background color? <a href=\"https://jsbin.com/ceyedapohu/2/edit?html,css,js,console,output\" target=\"_blank\" title=\"https://jsbin.com/ceyedapohu/2/edit?html,css,js,console,output\">https://jsbin.com/ceyedapohu/2/edit?html,css,js,console,output</a></p>",
        "id": 128681561,
        "sender_full_name": "Jake Goulding",
        "timestamp": 1530048916
    },
    {
        "content": "<blockquote>\n<p>is as fine as last time</p>\n</blockquote>\n<p>subtle <span class=\"emoji emoji-1f609\" title=\"wink\">:wink:</span></p>",
        "id": 128681741,
        "sender_full_name": "Jake Goulding",
        "timestamp": 1530049134
    },
    {
        "content": "<p>eg which would look this maybe ? <a href=\"/user_uploads/4715/1kBm1Vf5b-5Zif992cXZfj-p/pasted_image.png\" target=\"_blank\" title=\"pasted_image.png\">pasted image</a></p>\n<div class=\"message_inline_image\"><a href=\"/user_uploads/4715/1kBm1Vf5b-5Zif992cXZfj-p/pasted_image.png\" target=\"_blank\" title=\"pasted image\"><img src=\"/user_uploads/4715/1kBm1Vf5b-5Zif992cXZfj-p/pasted_image.png\"></a></div>",
        "id": 128681749,
        "sender_full_name": "lqd",
        "timestamp": 1530049149
    },
    {
        "content": "<p>Yeah. Course the problem then would be switching from dark text to light text</p>",
        "id": 128681822,
        "sender_full_name": "Jake Goulding",
        "timestamp": 1530049232
    },
    {
        "content": "<p>indeed</p>",
        "id": 128681830,
        "sender_full_name": "lqd",
        "timestamp": 1530049246
    },
    {
        "content": "<p>maybe just a line on the bottom 10% of the label?</p>",
        "id": 128681842,
        "sender_full_name": "Jake Goulding",
        "timestamp": 1530049269
    },
    {
        "content": "<p>seems... unlikely to be good</p>",
        "id": 128681846,
        "sender_full_name": "Jake Goulding",
        "timestamp": 1530049285
    },
    {
        "content": "<p><a href=\"https://css-tricks.com/reverse-text-color-mix-blend-mode/\" target=\"_blank\" title=\"https://css-tricks.com/reverse-text-color-mix-blend-mode/\">https://css-tricks.com/reverse-text-color-mix-blend-mode/</a></p>",
        "id": 128681909,
        "sender_full_name": "Jake Goulding",
        "timestamp": 1530049326
    },
    {
        "content": "<p><a href=\"/user_uploads/4715/P20kHc7zmzkyPLDorMbesAA-/pasted_image.png\" target=\"_blank\" title=\"pasted_image.png\">pasted image</a></p>\n<div class=\"message_inline_image\"><a href=\"/user_uploads/4715/P20kHc7zmzkyPLDorMbesAA-/pasted_image.png\" target=\"_blank\" title=\"pasted image\"><img src=\"/user_uploads/4715/P20kHc7zmzkyPLDorMbesAA-/pasted_image.png\"></a></div>",
        "id": 128681960,
        "sender_full_name": "lqd",
        "timestamp": 1530049437
    },
    {
        "content": "<p>not as bad as I expected. WDYT?</p>",
        "id": 128682044,
        "sender_full_name": "Jake Goulding",
        "timestamp": 1530049513
    },
    {
        "content": "<p>something feels, maybe a bit inconsistent with what we have so far ? at first I was apprehensive of the wide underlined empty space but now that I look at it, it's not as bad as I thought, like you said, maybe could work</p>",
        "id": 128682238,
        "sender_full_name": "lqd",
        "timestamp": 1530049778
    },
    {
        "content": "<p>Yeah, there's other things that have \"defaults\" and we don't care about those.</p>",
        "id": 128682301,
        "sender_full_name": "Jake Goulding",
        "timestamp": 1530049809
    },
    {
        "content": "<p>I'm trying to see how a kind of icon to the right of the label would look</p>",
        "id": 128682314,
        "sender_full_name": "lqd",
        "timestamp": 1530049841
    },
    {
        "content": "<p>like <a href=\"/user_uploads/4715/w8c9J1eCDC8bx56un8t8Phc7/pasted_image.png\" target=\"_blank\" title=\"pasted_image.png\">pasted image</a></p>\n<div class=\"message_inline_image\"><a href=\"/user_uploads/4715/w8c9J1eCDC8bx56un8t8Phc7/pasted_image.png\" target=\"_blank\" title=\"pasted image\"><img src=\"/user_uploads/4715/w8c9J1eCDC8bx56un8t8Phc7/pasted_image.png\"></a></div>",
        "id": 128682397,
        "sender_full_name": "lqd",
        "timestamp": 1530049927
    },
    {
        "content": "<p>not bad. My only concern is \"running out of space\"</p>",
        "id": 128682477,
        "sender_full_name": "Jake Goulding",
        "timestamp": 1530050055
    },
    {
        "content": "<p>wonder about as part of the value, not label</p>",
        "id": 128682504,
        "sender_full_name": "Jake Goulding",
        "timestamp": 1530050092
    },
    {
        "content": "<p>in a sense we already have \"default\", and in the value we'd have to use text or suffer styling issues (hello firefox), so à la \"2018 *\" \"2018 [not default]\" ?</p>",
        "id": 128682605,
        "sender_full_name": "lqd",
        "timestamp": 1530050228
    },
    {
        "content": "<p>(note for other people, in the little chevron next to a stream, you can open a menu, to mute it ;)</p>",
        "id": 128682695,
        "sender_full_name": "lqd",
        "timestamp": 1530050335
    },
    {
        "content": "<p>Oh, I meant <a href=\"user_uploads/4715/I0vq2w5vXUm4FssR43-c_KYr/pasted_image.png\" target=\"_blank\" title=\"user_uploads/4715/I0vq2w5vXUm4FssR43-c_KYr/pasted_image.png\">pasted image</a></p>\n<div class=\"message_inline_image\"><a href=\"user_uploads/4715/I0vq2w5vXUm4FssR43-c_KYr/pasted_image.png\" target=\"_blank\" title=\"pasted image\"><img src=\"user_uploads/4715/I0vq2w5vXUm4FssR43-c_KYr/pasted_image.png\"></a></div>",
        "id": 128682908,
        "sender_full_name": "Jake Goulding",
        "timestamp": 1530050423
    },
    {
        "content": "<p>oh ok next to the value interesting <a href=\"/user_uploads/4715/5WneygR84PcCTmWOvW0zkClc/pasted_image.png\" target=\"_blank\" title=\"pasted_image.png\">pasted image</a></p>\n<div class=\"message_inline_image\"><a href=\"/user_uploads/4715/5WneygR84PcCTmWOvW0zkClc/pasted_image.png\" target=\"_blank\" title=\"pasted image\"><img src=\"/user_uploads/4715/5WneygR84PcCTmWOvW0zkClc/pasted_image.png\"></a></div>",
        "id": 128683022,
        "sender_full_name": "lqd",
        "timestamp": 1530050555
    },
    {
        "content": "<p>makes sense as we're calling attention to the value, could be nice!</p>",
        "id": 128683033,
        "sender_full_name": "lqd",
        "timestamp": 1530050583
    },
    {
        "content": "<p>either on the left or right of the value, dunno.</p>",
        "id": 128683043,
        "sender_full_name": "Jake Goulding",
        "timestamp": 1530050598
    },
    {
        "content": "<p>let's see</p>",
        "id": 128683055,
        "sender_full_name": "lqd",
        "timestamp": 1530050616
    },
    {
        "content": "<p>although it would move around the value a bit, which could be annoying for the on/off selector</p>",
        "id": 128683058,
        "sender_full_name": "Jake Goulding",
        "timestamp": 1530050622
    },
    {
        "content": "<p>the dropdown is probably fine for the little movement, since the whole dropdown appears/disappears</p>",
        "id": 128683101,
        "sender_full_name": "Jake Goulding",
        "timestamp": 1530050644
    },
    {
        "content": "<p><a href=\"/user_uploads/4715/fN8alrfddY2-CRT8eQl2VbHF/pasted_image.png\" target=\"_blank\" title=\"pasted_image.png\">pasted image</a> it could be taking a %age of the label's width, and the value wouldn't move I don't think ?</p>\n<div class=\"message_inline_image\"><a href=\"/user_uploads/4715/fN8alrfddY2-CRT8eQl2VbHF/pasted_image.png\" target=\"_blank\" title=\"pasted image\"><img src=\"/user_uploads/4715/fN8alrfddY2-CRT8eQl2VbHF/pasted_image.png\"></a></div>",
        "id": 128683137,
        "sender_full_name": "lqd",
        "timestamp": 1530050732
    },
    {
        "content": "<p>or to the left of the note</p>",
        "id": 128683197,
        "sender_full_name": "lqd",
        "timestamp": 1530050816
    },
    {
        "content": "<p>and/or a colored left edge (but a bit more rounded than this screenshot, à la slack) <a href=\"/user_uploads/4715/Kz9dtrka6gtY5MyXl1pYCKqF/pasted_image.png\" target=\"_blank\" title=\"pasted_image.png\">pasted image</a></p>\n<div class=\"message_inline_image\"><a href=\"/user_uploads/4715/Kz9dtrka6gtY5MyXl1pYCKqF/pasted_image.png\" target=\"_blank\" title=\"pasted image\"><img src=\"/user_uploads/4715/Kz9dtrka6gtY5MyXl1pYCKqF/pasted_image.png\"></a></div>",
        "id": 128683284,
        "sender_full_name": "lqd",
        "timestamp": 1530050947
    },
    {
        "content": "<p><span class=\"user-mention\" data-user-id=\"116113\">@lqd</span>  OK, <em>not</em> an illusion <a href=\"/user_uploads/4715/iDtR8OjBZECSKXjIN3G3gBAW/pasted_image.png\" target=\"_blank\" title=\"pasted_image.png\">pasted image</a> </p>\n<div class=\"message_inline_image\"><a href=\"/user_uploads/4715/iDtR8OjBZECSKXjIN3G3gBAW/pasted_image.png\" target=\"_blank\" title=\"pasted image\"><img src=\"/user_uploads/4715/iDtR8OjBZECSKXjIN3G3gBAW/pasted_image.png\"></a></div><p>Not sure where it's coming from</p>",
        "id": 128742876,
        "sender_full_name": "Jake Goulding",
        "timestamp": 1530139933
    },
    {
        "content": "<p>so we're _not_ crazy which seems like good news</p>",
        "id": 128742968,
        "sender_full_name": "lqd",
        "timestamp": 1530140158
    },
    {
        "content": "<p>I can help locate it while triaging NLL bootstrap if you got a link btw</p>",
        "id": 128743078,
        "sender_full_name": "lqd",
        "timestamp": 1530140288
    },
    {
        "content": "<p>haha, it's all me being dumb </p>\n<p>I added a yellow fill, explicitly.</p>",
        "id": 128744292,
        "sender_full_name": "Jake Goulding",
        "timestamp": 1530142092
    },
    {
        "content": "<p>(disappear)</p>",
        "id": 128744296,
        "sender_full_name": "Jake Goulding",
        "timestamp": 1530142098
    },
    {
        "content": "<p><em>insert grandpa simpson old man yells at cloud meme but the old man is now me and the cloud has a kirby shape</em> :p (a kirby shep)</p>",
        "id": 128744317,
        "sender_full_name": "lqd",
        "timestamp": 1530142162
    },
    {
        "content": "<p>But if you care to follow along at home... <a href=\"http://97623c3a.ngrok.io/\" target=\"_blank\" title=\"http://97623c3a.ngrok.io/\">http://97623c3a.ngrok.io/</a></p>",
        "id": 128744457,
        "sender_full_name": "Jake Goulding",
        "timestamp": 1530142328
    },
    {
        "content": "<p><span class=\"user-mention\" data-user-id=\"116155\">@Jake Goulding</span> thanks :)</p>",
        "id": 128744556,
        "sender_full_name": "lqd",
        "timestamp": 1530142479
    },
    {
        "content": "<p>but also: <a href=\"/user_uploads/4715/fxpBuOxDJvmyONB1iYzJK8il/pasted_image.png\" target=\"_blank\" title=\"pasted_image.png\">pasted image</a></p>\n<div class=\"message_inline_image\"><a href=\"/user_uploads/4715/fxpBuOxDJvmyONB1iYzJK8il/pasted_image.png\" target=\"_blank\" title=\"pasted image\"><img src=\"/user_uploads/4715/fxpBuOxDJvmyONB1iYzJK8il/pasted_image.png\"></a></div>",
        "id": 128744560,
        "sender_full_name": "lqd",
        "timestamp": 1530142486
    },
    {
        "content": "<p>Hmm. a @lqd self portrait</p>",
        "id": 128744671,
        "sender_full_name": "Jake Goulding",
        "timestamp": 1530142665
    },
    {
        "content": "<p>advanced options looking good</p>",
        "id": 128744876,
        "sender_full_name": "lqd",
        "timestamp": 1530142925
    },
    {
        "content": "<p>nicely done</p>",
        "id": 128744879,
        "sender_full_name": "lqd",
        "timestamp": 1530142934
    },
    {
        "content": "<p>also makes me notice how Open Sans semibold 'E' is way shorter than the regular E</p>",
        "id": 128744901,
        "sender_full_name": "lqd",
        "timestamp": 1530142983
    },
    {
        "content": "<p>I'm thinking that the \"non-default\" UI is good enough for a first cut</p>",
        "id": 128745192,
        "sender_full_name": "Jake Goulding",
        "timestamp": 1530143427
    },
    {
        "content": "<p><span class=\"user-mention\" data-user-id=\"116113\">@lqd</span> you gonna make me change the fonts?</p>",
        "id": 128745203,
        "sender_full_name": "Jake Goulding",
        "timestamp": 1530143443
    },
    {
        "content": "<p>old man yells at font</p>",
        "id": 128745220,
        "sender_full_name": "lqd",
        "timestamp": 1530143479
    },
    {
        "content": "<p>where do you even notice that?</p>",
        "id": 128745222,
        "sender_full_name": "Jake Goulding",
        "timestamp": 1530143483
    },
    {
        "content": "<p><a href=\"/user_uploads/4715/7LCVP3owQC3Q5IPPeOt8rXkT/pasted_image.png\" target=\"_blank\" title=\"pasted_image.png\">pasted image</a>  vs <a href=\"/user_uploads/4715/87MJ8-26GCXzaK9VkJck_1PH/pasted_image.png\" target=\"_blank\" title=\"pasted_image.png\">pasted image</a></p>\n<div class=\"message_inline_image\"><a href=\"/user_uploads/4715/7LCVP3owQC3Q5IPPeOt8rXkT/pasted_image.png\" target=\"_blank\" title=\"pasted image\"><img src=\"/user_uploads/4715/7LCVP3owQC3Q5IPPeOt8rXkT/pasted_image.png\"></a></div><div class=\"message_inline_image\"><a href=\"/user_uploads/4715/87MJ8-26GCXzaK9VkJck_1PH/pasted_image.png\" target=\"_blank\" title=\"pasted image\"><img src=\"/user_uploads/4715/87MJ8-26GCXzaK9VkJck_1PH/pasted_image.png\"></a></div>",
        "id": 128745294,
        "sender_full_name": "lqd",
        "timestamp": 1530143568
    },
    {
        "content": "<p>For some value of \"way\"</p>",
        "id": 128745315,
        "sender_full_name": "Jake Goulding",
        "timestamp": 1530143611
    },
    {
        "content": "<p>\"non-default UI\" meaning this advanced options popover ?</p>",
        "id": 128745322,
        "sender_full_name": "lqd",
        "timestamp": 1530143634
    },
    {
        "content": "<p>(with only the Edition selector for now, I assume as well ?)</p>",
        "id": 128745375,
        "sender_full_name": "lqd",
        "timestamp": 1530143678
    },
    {
        "content": "<p>if so, agreed <span class=\"emoji emoji-1f4af\" title=\"100\">:100:</span> <span class=\"emoji emoji-1f6a2\" title=\"ship\">:ship:</span> it, <span class=\"emoji emoji-1f411\" title=\"sheep\">:sheep:</span> it, :shep: it</p>",
        "id": 128745480,
        "sender_full_name": "lqd",
        "timestamp": 1530143839
    },
    {
        "content": "<p>\"non-default UI\" -&gt; The UI aspects that indicate \"hey, something is set in this menu\". The colored icon and the bolded label.</p>\n<p>Yeah, the backtrace and rustflags are hanging out from your original code. Leaving them in that sidebranch until I implement them.</p>\n<p>Can't ship it <em>quite</em> yet. Got to figure out the URL story.</p>",
        "id": 128752357,
        "sender_full_name": "Jake Goulding",
        "timestamp": 1530156712
    },
    {
        "content": "<p><span class=\"user-mention\" data-user-id=\"116113\">@lqd</span> do you think it's silly to have {default,2015,2018}?</p>",
        "id": 128835917,
        "sender_full_name": "Jake Goulding",
        "timestamp": 1530287931
    },
    {
        "content": "<p>Should I just have 2015/2018</p>",
        "id": 128835918,
        "sender_full_name": "Jake Goulding",
        "timestamp": 1530287938
    },
    {
        "content": "<p>I guess this is going to matter more during the transition period ?</p>",
        "id": 128836001,
        "sender_full_name": "lqd",
        "timestamp": 1530288013
    },
    {
        "content": "<p>that is, until the switch, we'll always be \"default = 2015\", and then \"default = 2018\"</p>",
        "id": 128836017,
        "sender_full_name": "lqd",
        "timestamp": 1530288049
    },
    {
        "content": "<p>(and the little \"blue indicator that something is up to no good\" will switch its active/inactive rules as well)</p>",
        "id": 128836056,
        "sender_full_name": "lqd",
        "timestamp": 1530288114
    },
    {
        "content": "<p>it does seem simpler to just have 2015/2018, and we handle the default when the transition period is over ?</p>",
        "id": 128836110,
        "sender_full_name": "lqd",
        "timestamp": 1530288155
    },
    {
        "content": "<p>Yeah, and just have a commit at that point. Means that the playground will have a different default than cargo.</p>",
        "id": 128836197,
        "sender_full_name": "Jake Goulding",
        "timestamp": 1530288264
    },
    {
        "content": "<p>why ? I'm not that familiar with the plans around the default edition value in cargo :/</p>",
        "id": 128836332,
        "sender_full_name": "lqd",
        "timestamp": 1530288426
    },
    {
        "content": "<p>Well, it would have a different default for a period of time until I updated the playground</p>",
        "id": 128836403,
        "sender_full_name": "Jake Goulding",
        "timestamp": 1530288537
    },
    {
        "content": "<p>yeah that for sure</p>",
        "id": 128836422,
        "sender_full_name": "lqd",
        "timestamp": 1530288559
    },
    {
        "content": "<p>But AFAIK, <code>cargo new</code> will set <code>edition = \"2018\"</code> at some point</p>",
        "id": 128836425,
        "sender_full_name": "Jake Goulding",
        "timestamp": 1530288561
    },
    {
        "content": "<p>could we ask cargo what its default edition is, the same way we ask its version?</p>",
        "id": 128836488,
        "sender_full_name": "lqd",
        "timestamp": 1530288611
    },
    {
        "content": "<p>(without hacking a <code>cargo new </code> &amp;&amp; grep 2018 )</p>",
        "id": 128836499,
        "sender_full_name": "lqd",
        "timestamp": 1530288637
    },
    {
        "content": "<p>Well, we ask the version by running <code>rustc --version</code> and grepping the output ;-)</p>",
        "id": 128837038,
        "sender_full_name": "Jake Goulding",
        "timestamp": 1530289388
    },
    {
        "content": "<p>:)</p>",
        "id": 128837041,
        "sender_full_name": "lqd",
        "timestamp": 1530289406
    },
    {
        "content": "<p>we could have a different default for a short while until the playground is updated; if it's a different default for months then ok maybe it's worth thinking about it; but if it's days, it doesn't seem like a crazy situation, not mentioning people will have the same issue locally until they rustup to stable ¯\\_(ツ)_/¯</p>",
        "id": 128837123,
        "sender_full_name": "lqd",
        "timestamp": 1530289511
    },
    {
        "content": "<p>That's a good analogy.</p>",
        "id": 128837599,
        "sender_full_name": "Jake Goulding",
        "timestamp": 1530290065
    },
    {
        "content": "<p><span class=\"user-mention\" data-user-id=\"116113\">@lqd</span> of course, now I have to decide if I leave it a dropdown or make it the fancy 2-value choice</p>",
        "id": 128838611,
        "sender_full_name": "Jake Goulding",
        "timestamp": 1530291469
    },
    {
        "content": "<p>the 2-value choice seemed consistent with the rest WDYT ?</p>",
        "id": 128838661,
        "sender_full_name": "lqd",
        "timestamp": 1530291517
    },
    {
        "content": "<p>yeah, but then I have to change the code in 3 years :-)</p>",
        "id": 128838805,
        "sender_full_name": "Jake Goulding",
        "timestamp": 1530291701
    },
    {
        "content": "<p>haha true</p>",
        "id": 128838851,
        "sender_full_name": "lqd",
        "timestamp": 1530291723
    },
    {
        "content": "<p>Ok, want to play with the feel any? <a href=\"https://c3ac9cf9.ngrok.io\" target=\"_blank\" title=\"https://c3ac9cf9.ngrok.io\">https://c3ac9cf9.ngrok.io</a></p>",
        "id": 128839135,
        "sender_full_name": "Jake Goulding",
        "timestamp": 1530292085
    },
    {
        "content": "<p>oh yeah a side effect is now that switching to stable can change the edition</p>",
        "id": 128839245,
        "sender_full_name": "lqd",
        "timestamp": 1530292228
    },
    {
        "content": "<p>which makes sense ofc</p>",
        "id": 128839257,
        "sender_full_name": "lqd",
        "timestamp": 1530292247
    },
    {
        "content": "<p>did you want to keep your bold+color style on the Edition label when it is not the default (now that it's not using a dropdown anymore) ?</p>",
        "id": 128839279,
        "sender_full_name": "lqd",
        "timestamp": 1530292312
    },
    {
        "content": "<p>oh, yeah. that's what i get for being lazy the first time around</p>",
        "id": 128839894,
        "sender_full_name": "Jake Goulding",
        "timestamp": 1530293107
    },
    {
        "content": "<p>OK, fixed</p>",
        "id": 128840171,
        "sender_full_name": "Jake Goulding",
        "timestamp": 1530293464
    },
    {
        "content": "<p>looks good to me :) (I don't think we'll be able to do anything about the Advanced dialogs popover moving slightly to the right when the channel switches from Stable to the longer Nightly)</p>",
        "id": 128840477,
        "sender_full_name": "lqd",
        "timestamp": 1530293859
    },
    {
        "content": "<p><span class=\"user-mention\" data-user-id=\"116155\">@Jake Goulding</span> <a href=\"https://c3ac9cf9.ngrok.io/?version=nightly&amp;mode=debug&amp;edition=2015\" target=\"_blank\" title=\"https://c3ac9cf9.ngrok.io/?version=nightly&amp;mode=debug&amp;edition=2015\">https://c3ac9cf9.ngrok.io/?version=nightly&amp;mode=debug&amp;edition=2015</a> switch to 2018 and the Edition label won't have its styling applied ? but it definitely works in other cases I've tried</p>",
        "id": 128840579,
        "sender_full_name": "lqd",
        "timestamp": 1530293983
    },
    {
        "content": "<p>uhhh. I swear I saw it do that for a second, but now I cannot repro...</p>",
        "id": 128840690,
        "sender_full_name": "Jake Goulding",
        "timestamp": 1530294119
    },
    {
        "content": "<p><span class=\"user-mention\" data-user-id=\"116155\">@Jake Goulding</span> you already shipped it, nice :D</p>",
        "id": 128986973,
        "sender_full_name": "lqd",
        "timestamp": 1530565037
    },
    {
        "content": "<p>@lqd Yeah, I <span class=\"emoji emoji-2764\" title=\"heart\">:heart:</span>  those subtle releases. You are the first to mention it in ~ 4 days</p>",
        "id": 129035261,
        "sender_full_name": "Jake Goulding",
        "timestamp": 1530637297
    },
    {
        "content": "<p>all the share urls changed it was hard to miss for me even without visiting the playground :)</p>",
        "id": 129035323,
        "sender_full_name": "lqd",
        "timestamp": 1530637363
    },
    {
        "content": "<p>in any case: congrats for a smooth launch <span class=\"emoji emoji-1f389\" title=\"tada\">:tada:</span> + it's very cool</p>",
        "id": 129035343,
        "sender_full_name": "lqd",
        "timestamp": 1530637393
    },
    {
        "content": "<p>Yeah, I kind of want to add my own \"tracking pixel\" to the share links because it was fun watching those show up</p>",
        "id": 129035429,
        "sender_full_name": "Jake Goulding",
        "timestamp": 1530637477
    },
    {
        "content": "<p>you mean, in a different way than just checking the logs for \"edition=\"?</p>",
        "id": 129035570,
        "sender_full_name": "lqd",
        "timestamp": 1530637622
    },
    {
        "content": "<p>I mean so I can do it for any given release. moral equivalent of <code>&amp;playground-release=SHA</code></p>",
        "id": 129035683,
        "sender_full_name": "Jake Goulding",
        "timestamp": 1530637751
    },
    {
        "content": "<p>which is silly, of course</p>",
        "id": 129035687,
        "sender_full_name": "Jake Goulding",
        "timestamp": 1530637759
    },
    {
        "content": "<p>oh, yeah understood</p>",
        "id": 129035785,
        "sender_full_name": "lqd",
        "timestamp": 1530637807
    },
    {
        "content": "<p>we could handle the shortlink ourselves and save the playground rev at the same time as the code :3</p>",
        "id": 129035797,
        "sender_full_name": "lqd",
        "timestamp": 1530637834
    },
    {
        "content": "<p>not sure what you mean by handle it ourselves — how are we not already doing so?</p>",
        "id": 129035914,
        "sender_full_name": "Jake Goulding",
        "timestamp": 1530638009
    },
    {
        "content": "<p>we do, but I meant that we do not store additional information on them</p>",
        "id": 129035988,
        "sender_full_name": "lqd",
        "timestamp": 1530638088
    },
    {
        "content": "<p>which you would have to do if one did shortlinks à la twitter, say</p>",
        "id": 129036003,
        "sender_full_name": "lqd",
        "timestamp": 1530638110
    },
    {
        "content": "<p>we could add it to the gist for sure tho</p>",
        "id": 129036021,
        "sender_full_name": "lqd",
        "timestamp": 1530638136
    },
    {
        "content": "<p>and in a number of ways :) in the \"Code shared from the Rust Playground\" comment, in the filename, in another file in the gist (like the idea of saving the cargo.toml there) etc</p>",
        "id": 129036115,
        "sender_full_name": "lqd",
        "timestamp": 1530638223
    },
    {
        "content": "<p>you were reading in Discord, eh? ;-)</p>",
        "id": 129036124,
        "sender_full_name": "Jake Goulding",
        "timestamp": 1530638243
    },
    {
        "content": "<p>sometimes :3</p>",
        "id": 129036131,
        "sender_full_name": "lqd",
        "timestamp": 1530638262
    },
    {
        "content": "<p>in a more traditional webapp you could store it in the database and be done with it; here it would be harder for us to store anything on GH which we would want to query later I presume</p>",
        "id": 129036203,
        "sender_full_name": "lqd",
        "timestamp": 1530638314
    },
    {
        "content": "<p>not harder harder, just have to be more cautious. It's a write-once DB ;-)</p>",
        "id": 129036228,
        "sender_full_name": "Jake Goulding",
        "timestamp": 1530638369
    },
    {
        "content": "<p>storing the rev in the \"code shared\" seems easy to do; and I wonder if we can get gists in bulk from GH, to do the stat you want</p>",
        "id": 129036293,
        "sender_full_name": "lqd",
        "timestamp": 1530638426
    },
    {
        "content": "<p>The thing about the rev is that really there should only ever be a small number. The caching should expire after 24h, so it's up to how many releases are pushed in that window.</p>",
        "id": 129036411,
        "sender_full_name": "Jake Goulding",
        "timestamp": 1530638556
    },
    {
        "content": "<p>@lqd do you recall where you got the SVGs for the playground? I'm looking to see if there's a clipboard one</p>",
        "id": 129711243,
        "sender_full_name": "Jake Goulding",
        "timestamp": 1531678475
    },
    {
        "content": "<p><span class=\"user-mention\" data-user-id=\"116155\">@Jake Goulding</span> yeah I think from the Material Design site <a href=\"https://material.io/tools/icons/?style=baseline\" target=\"_blank\" title=\"https://material.io/tools/icons/?style=baseline\">https://material.io/tools/icons/?style=baseline</a> (btw <a href=\"https://play.rust-lang.org/\" target=\"_blank\" title=\"https://play.rust-lang.org/\">https://play.rust-lang.org/</a> 502s :/)</p>",
        "id": 129712918,
        "sender_full_name": "lqd",
        "timestamp": 1531681520
    },
    {
        "content": "<p>Not 502ing for me</p>",
        "id": 129713161,
        "sender_full_name": "simulacrum",
        "timestamp": 1531681901
    },
    {
        "content": "<p>oh, wait, just browser cache</p>",
        "id": 129713165,
        "sender_full_name": "simulacrum",
        "timestamp": 1531681916
    },
    {
        "content": "<p>ah jeez</p>",
        "id": 129713403,
        "sender_full_name": "Jake Goulding",
        "timestamp": 1531682325
    },
    {
        "content": "<p>for about an hour</p>",
        "id": 129713408,
        "sender_full_name": "Jake Goulding",
        "timestamp": 1531682330
    },
    {
        "content": "<p>Should be back; checking the cause</p>",
        "id": 129713548,
        "sender_full_name": "Jake Goulding",
        "timestamp": 1531682570
    },
    {
        "content": "<div class=\"codehilite\"><pre><span></span>Jul 15 18:04:29 ip-172-30-0-53 kernel: [1312205.811843] nginx invoked oom-killer: gfp_mask=0x24201ca, order=0, oom_score_adj=0\nJul 15 18:04:29 ip-172-30-0-53 kernel: [1312205.812250] Out of memory: Kill process 5008 (ui) score 865 or sacrifice child\nJul 15 18:04:29 ip-172-30-0-53 kernel: [1312205.822342] Killed process 13376 (docker) total-vm:174904kB, anon-rss:6228kB, file-rss:552kB\n</pre></div>",
        "id": 129713616,
        "sender_full_name": "Jake Goulding",
        "timestamp": 1531682748
    },
    {
        "content": "<p>hmmmmm</p>",
        "id": 129713620,
        "sender_full_name": "Jake Goulding",
        "timestamp": 1531682754
    },
    {
        "content": "<p>Also, doh:</p>\n<div class=\"codehilite\"><pre><span></span>Jul 15 19:23:06 ip-172-30-0-53 CRON[15702]: (CRON) info (No MTA installed, discarding output)\n</pre></div>",
        "id": 129713660,
        "sender_full_name": "Jake Goulding",
        "timestamp": 1531682800
    },
    {
        "content": "<div class=\"codehilite\"><pre><span></span>[ pid ]   uid  tgid total_vm      rss nr_ptes nr_pmds swapents oom_score_adj name\n[  379]     0   379    12491     3683      29       3      420             0 systemd-journal\n[  432]     0   432    25742       73      17       3       28             0 lvmetad\n[  464]     0   464    10649      362      23       3       11         -1000 systemd-udevd\n[  588]   100   588    25081      318      19       3       44             0 systemd-timesyn\n[  956]     0   956     4030      239      13       3      152             0 dhclient\n[ 1160]     0  1160    68622      824      36       3      205             0 accounts-daemon\n[ 1161]     0  1161   192433    14852     116       5     2938          -500 dockerd\n[ 1164]     0  1164     7154      132      18       3        1             0 systemd-logind\n[ 1165]   104  1165    65157      878      29       4       74             0 rsyslogd\n[ 1179]     0  1179     1099      302       8       4        8             0 acpid\n[ 1182]     0  1182     6511      341      17       3        8             0 atd\n[ 1186]     0  1186     6932      440      19       3       12             0 cron\n[ 1190]   107  1190    10754      324      26       3        0          -900 dbus-daemon\n[ 1195]     0  1195     1305       14       8       3       15             0 iscsid\n[ 1196]     0  1196     1430      877       9       3        0           -17 iscsid\n[ 1227]     0  1227    16377      517      36       3        5         -1000 sshd\n[ 1229]     0  1229    76936     2885      37       5      328          -900 snapd\n[ 1231]     0  1231   208104      988      35       4        0             0 lxcfs\n[ 1251]     0  1251     3343      209      11       3       10             0 mdadm\n[ 1255]     0  1255    31464      534      50       3       88             0 nginx\n[ 1266]     0  1266    69277      259      38       3        6             0 polkitd\n[ 1332]     0  1332     4868      426      14       3        0             0 irqbalance\n[ 1344]     0  1344     3664      349      12       3       25             0 agetty\n[ 1354]     0  1354     3618      366      12       3       36             0 agetty\n[ 1369]     0  1369   241834     5665      65       6      809          -500 docker-containe\n[ 5008]     0  5008  2207936  1795292    4034      12   256849             0 ui\n[13671]    33 13671    31612      802      48       3       72             0 nginx\n[13672]    33 13672    31612      883      48       3       72             0 nginx\n[13457]     0 13457     1833      130       8       5        0          -999 docker-containe\n[13459]     0 13459     1897      128       8       5        0          -999 docker-containe\n[13460]     0 13460     1833      122       8       5        0          -999 docker-containe\n[13478]     0 13478    48656     1753      25       5        0          -999 docker-runc\n[13482]     0 13482    32624     1307      25       5        0          -999 docker-runc\n[13492]     0 13492    32272     1306      24       5        0          -999 docker-runc\n[13518]     0 13518    11462     1052      19       5        0             0 runc:[2:INIT]\n[13548]     0 13548    11462     1066      20       5        0             0 runc:[2:INIT]\n[13560]     0 13560    33912     4907      59       6        0          -999 exe\n[13563]     0 13563    11462     1056      20       6        0             0 runc:[2:INIT]\n[13567]     0 13567    33912     4910      60       5        0          -999 exe\n[13568]     0 13568    34264     5038      59       5        0          -999 exe\n[13582]     0 13582    24130     2193      32       3        0          -500 exe\n[13583]     0 13583    24130     2622      33       3        0          -500 exe\n[13584]     0 13584    24130     2340      31       4        0          -500 exe\n[13609]     0 13609    10649      559      21       3       11             0 systemd-udevd\n[13610]     0 13610    10649      400      21       3       11             0 systemd-udevd\n[13611]     0 13611    10649      527      21       3       11             0 systemd-udevd\n[13612]     0 13612    10649      369      21       3       11             0 systemd-udevd\n[13613]     0 13613    10649      369      21       3       11             0 systemd-udevd\n[13614]     0 13614    10649      213      21       3       11             0 systemd-udevd\n</pre></div>",
        "id": 129713804,
        "sender_full_name": "Jake Goulding",
        "timestamp": 1531683115
    },
    {
        "content": "<p>I wonder if someone tried to do the equivalent of <code>cat /dev/urandom</code></p>",
        "id": 129713845,
        "sender_full_name": "Jake Goulding",
        "timestamp": 1531683149
    },
    {
        "content": "<p><span class=\"user-mention\" data-user-id=\"116113\">@lqd</span> do you think you could help me identify which icons are which?</p>",
        "id": 129714774,
        "sender_full_name": "Jake Goulding",
        "timestamp": 1531684835
    },
    {
        "content": "<p>And did we make changes to the originals?</p>",
        "id": 129714881,
        "sender_full_name": "Jake Goulding",
        "timestamp": 1531685040
    },
    {
        "content": "<p>Tonight it’s gonna be hard but you can ask questions and I’ll answer in the morning — I made no changes, and they should be « cog » ,« chevron » or similar, « help », I think. You can search on this site btw, it’s helpful sometimes when there are many icons</p>",
        "id": 129715009,
        "sender_full_name": "lqd",
        "timestamp": 1531685234
    },
    {
        "content": "<p>No worries on time. I was using the browser's control-f find, is that what you mean?</p>",
        "id": 129715065,
        "sender_full_name": "Jake Goulding",
        "timestamp": 1531685289
    },
    {
        "content": "<p>The icons I'm downloading have like all 5 variants in them, which is odd</p>",
        "id": 129715069,
        "sender_full_name": "Jake Goulding",
        "timestamp": 1531685311
    },
    {
        "content": "<p>IIRC there is a search field on the left — but this all changed recently after we updated the playground so I might not be up to speed</p>",
        "id": 129716630,
        "sender_full_name": "lqd",
        "timestamp": 1531688217
    },
    {
        "content": "<p><span class=\"user-mention\" data-user-id=\"116155\">@Jake Goulding</span> from right to left \"help_outline\", \"keyboard_arrow_down\", \"settings\", \"more_horiz\" I think and finally \"play_arrow\"</p>",
        "id": 129717245,
        "sender_full_name": "lqd",
        "timestamp": 1531689294
    },
    {
        "content": "<p>Neat, thank you!</p>",
        "id": 129717415,
        "sender_full_name": "Jake Goulding",
        "timestamp": 1531689592
    },
    {
        "content": "<p>Working on: <a href=\"/user_uploads/4715/_NDvqgpxGygxrSXQtmXPlI4e/copy.gif\" target=\"_blank\" title=\"copy.gif\">copy.gif</a></p>\n<div class=\"message_inline_image\"><a href=\"/user_uploads/4715/_NDvqgpxGygxrSXQtmXPlI4e/copy.gif\" target=\"_blank\" title=\"copy.gif\"><img src=\"/user_uploads/4715/_NDvqgpxGygxrSXQtmXPlI4e/copy.gif\"></a></div>",
        "id": 129717462,
        "sender_full_name": "Jake Goulding",
        "timestamp": 1531689611
    },
    {
        "content": "<p>Btw I love that copy button so much, thanks :D &lt;3</p>",
        "id": 130784173,
        "sender_full_name": "RalfJ",
        "timestamp": 1533222849
    },
    {
        "content": "<p>Oh yea, recent playpen upgrades are totally rad. I already used a bunch of them</p>",
        "id": 130784212,
        "sender_full_name": "oli",
        "timestamp": 1533222900
    },
    {
        "content": "<p>a couple \"title\" tooltips would be super nice (sorry Jake I'm abroad, I can do a PR in a couple weeks though)</p>",
        "id": 130786873,
        "sender_full_name": "lqd",
        "timestamp": 1533225798
    },
    {
        "content": "<blockquote>\n<p>a couple \"title\" tooltips would be super nice</p>\n</blockquote>\n<p><span class=\"user-mention\" data-user-id=\"116113\">@lqd</span>  On which?</p>",
        "id": 130856932,
        "sender_full_name": "Jake Goulding",
        "timestamp": 1533323489
    },
    {
        "content": "<p>on the icon buttons copying the urls</p>",
        "id": 130857019,
        "sender_full_name": "lqd",
        "timestamp": 1533323581
    },
    {
        "content": "<p>as feedforward to know what clicking them will do</p>",
        "id": 130857031,
        "sender_full_name": "lqd",
        "timestamp": 1533323598
    },
    {
        "content": "<p>Alright, what are good one-word verbs for \"produce {LLVM IR, MIR, WebAssembly} output\"? /cc <span class=\"user-mention\" data-user-id=\"116113\">@lqd</span></p>",
        "id": 131139303,
        "sender_full_name": "Jake Goulding",
        "timestamp": 1533772050
    },
    {
        "content": "<p>For example, making assembly is \"assemble\"</p>",
        "id": 131139305,
        "sender_full_name": "Jake Goulding",
        "timestamp": 1533772066
    },
    {
        "content": "<p>And there's Build / Run / Test already</p>",
        "id": 131139310,
        "sender_full_name": "Jake Goulding",
        "timestamp": 1533772081
    },
    {
        "content": "<p>if you ask <span class=\"user-mention\" data-user-id=\"116113\">@lqd</span> they'll reply you with <span class=\"emoji emoji-1f438\" title=\"frog\">:frog:</span></p>",
        "id": 131140140,
        "sender_full_name": "Keith Yeung",
        "timestamp": 1533773210
    },
    {
        "content": "<p>\"compile\"?   <span class=\"user-mention\" data-user-id=\"116155\">@Jake Goulding</span></p>",
        "id": 131151602,
        "sender_full_name": "Charles Lew",
        "timestamp": 1533792138
    },
    {
        "content": "<p><span class=\"user-mention\" data-user-id=\"116155\">@Jake Goulding</span>  TBH I think this is also \"Build\"</p>",
        "id": 131156446,
        "sender_full_name": "RalfJ",
        "timestamp": 1533800736
    },
    {
        "content": "<p>which is \"produce {binary, assembly, LLVM, MIR, wasm} output\"</p>",
        "id": 131156448,
        "sender_full_name": "RalfJ",
        "timestamp": 1533800751
    },
    {
        "content": "<p>I'm used to \"emit\" but that might be because of the flag</p>",
        "id": 131157345,
        "sender_full_name": "lqd",
        "timestamp": 1533802071
    },
    {
        "content": "<p>\"Build\" and \"compile to\" also make a lot of sense indeed, especially sInce  in other languages where they probably wouldn't say \"emit\"</p>",
        "id": 131157476,
        "sender_full_name": "lqd",
        "timestamp": 1533802297
    },
    {
        "content": "<p>For MIR, you could use “Launch” ;)</p>",
        "id": 131157477,
        "sender_full_name": "pnkfelix",
        "timestamp": 1533802298
    },
    {
        "content": "<p><span class=\"emoji emoji-1f680\" title=\"rocket\">:rocket:</span></p>",
        "id": 131157480,
        "sender_full_name": "lqd",
        "timestamp": 1533802321
    },
    {
        "content": "<p><span class=\"user-mention\" data-user-id=\"120791\">@RalfJ</span> but if the button changes to \"build\" for 3/4 different actions, it's not <em>super</em> useful to tell what's going on</p>",
        "id": 131170243,
        "sender_full_name": "Jake Goulding",
        "timestamp": 1533819527
    },
    {
        "content": "<p><span class=\"user-mention\" data-user-id=\"116083\">@pnkfelix</span> I do like the phrasing, but would worry people would think it would run the MIR e.g. miri</p>",
        "id": 131170654,
        "sender_full_name": "Jake Goulding",
        "timestamp": 1533819913
    },
    {
        "content": "<blockquote>\n<p>For example, making assembly is \"assemble\"</p>\n</blockquote>\n<p>\"Assemble\" is ASM → Binary, but playground is doing Rust → ASM. I think \"Compile\" is more appriopriate.</p>",
        "id": 131170862,
        "sender_full_name": "kennytm",
        "timestamp": 1533820149
    },
    {
        "content": "<p><span class=\"user-mention\" data-user-id=\"116155\">@Jake Goulding</span> true. so were you asking for 4 different verbs?</p>",
        "id": 131171408,
        "sender_full_name": "RalfJ",
        "timestamp": 1533820690
    },
    {
        "content": "<p>if we're talking about this for the \"redo what you just did\" use case, at the time I was thinking the button label would just have what it emits: 1) you choose the MIR option in the popover, 2) then the main button label switches to MIR</p>",
        "id": 131171412,
        "sender_full_name": "lqd",
        "timestamp": 1533820701
    },
    {
        "content": "<blockquote>\n<p><span class=\"user-mention\" data-user-id=\"116083\">@pnkfelix</span> I do like the phrasing, but would worry people would think it would run the MIR e.g. miri</p>\n</blockquote>\n<p>well you could go super obtuse and use the verb \"orbit\" for generating MIR</p>",
        "id": 131171434,
        "sender_full_name": "pnkfelix",
        "timestamp": 1533820747
    },
    {
        "content": "<p>(because that is a rather \"advanced\" playground use case where users would know that it's about the produced artefacts, and where the verb didn't seem 100% necessary; but if we absolutely need one, something like \"emit MIR\" also has the advantage of being short)</p>",
        "id": 131171555,
        "sender_full_name": "lqd",
        "timestamp": 1533820884
    },
    {
        "content": "<p>if \"Build\" is preferred for the artefacts actions, I guess building libs can also switch to \"Check\" to free up \"Build\"</p>",
        "id": 131171674,
        "sender_full_name": "lqd",
        "timestamp": 1533821019
    },
    {
        "content": "<p><span class=\"user-mention\" data-user-id=\"116113\">@lqd</span> if the analogue is <code>cargo check</code> vs <code>cargo build</code>, note that <code>cargo check</code> won't invoke LLVM so e.g. <code>cargo check</code> won't catch errors like this:</p>\n<div class=\"codehilite\"><pre><span></span><span class=\"cp\">#![feature(asm)]</span><span class=\"w\"></span>\n<span class=\"cp\">#![crate_type = </span><span class=\"s\">&quot;lib&quot;</span><span class=\"cp\">]</span><span class=\"w\"></span>\n<span class=\"k\">pub</span><span class=\"w\"> </span><span class=\"k\">unsafe</span><span class=\"w\"> </span><span class=\"k\">fn</span> <span class=\"nf\">foo</span><span class=\"p\">()</span><span class=\"w\"> </span><span class=\"p\">{</span><span class=\"w\"></span>\n<span class=\"w\">    </span><span class=\"n\">asm</span><span class=\"o\">!</span><span class=\"p\">(</span><span class=\"s\">&quot;asdadasdasdas&quot;</span><span class=\"p\">);</span><span class=\"w\"></span>\n<span class=\"p\">}</span><span class=\"w\"></span>\n</pre></div>",
        "id": 131174188,
        "sender_full_name": "kennytm",
        "timestamp": 1533823540
    },
    {
        "content": "<p>it could be just labeling it doesn't have to be \"cargo check\"</p>",
        "id": 131174242,
        "sender_full_name": "lqd",
        "timestamp": 1533823579
    },
    {
        "content": "<p>this is just the playground UI rather than its backend IIUC</p>",
        "id": 131174262,
        "sender_full_name": "lqd",
        "timestamp": 1533823608
    },
    {
        "content": "<p>i understand, a concern would be <code>check</code> and <code>cargo check</code> would be subtly different (the playground <code>check</code> being bit stricter)</p>",
        "id": 131174359,
        "sender_full_name": "kennytm",
        "timestamp": 1533823687
    },
    {
        "content": "<p>understood, diverging the meaning of Check would be a concern indeed.  “emit” for the MIR/etc actions might then be a good candidate. Or “show MIR” or “MIR”</p>",
        "id": 131175504,
        "sender_full_name": "lqd",
        "timestamp": 1533824734
    },
    {
        "content": "<p>(I’m going through hell typing on the Zulip mobile app :) randomly capitalizing or switching case)</p>",
        "id": 131175585,
        "sender_full_name": "lqd",
        "timestamp": 1533824804
    },
    {
        "content": "<blockquote>\n<p>Or “show MIR” or “MIR”</p>\n</blockquote>\n<p>agreed. if we don't need a single verb for all actions, explicitly saying ASM / LLVM / MIR / WASM feels better</p>",
        "id": 131175613,
        "sender_full_name": "kennytm",
        "timestamp": 1533824844
    },
    {
        "content": "<p>And I like \"show\"</p>",
        "id": 131178122,
        "sender_full_name": "Jake Goulding",
        "timestamp": 1533827198
    },
    {
        "content": "<p>Yeah, it doesn't <em>have</em> to be one word, but it has to be short</p>\n<p><a href=\"/user_uploads/4715/2FNCF136qsRpQ71cAu8XV70I/pasted_image.png\" target=\"_blank\" title=\"pasted_image.png\">pasted image</a></p>\n<div class=\"message_inline_image\"><a href=\"/user_uploads/4715/2FNCF136qsRpQ71cAu8XV70I/pasted_image.png\" target=\"_blank\" title=\"pasted image\"><img src=\"/user_uploads/4715/2FNCF136qsRpQ71cAu8XV70I/pasted_image.png\"></a></div>",
        "id": 131178173,
        "sender_full_name": "Jake Goulding",
        "timestamp": 1533827270
    },
    {
        "content": "<p>I'd probably avoid \"check\" because some people have requested an actual check (although I'm not clear on the benefit yet)</p>",
        "id": 131178253,
        "sender_full_name": "Jake Goulding",
        "timestamp": 1533827314
    },
    {
        "content": "<p>Semirelated: it's annoying that <code>cargo build</code> doesn't generate artifacts that <code>cargo check</code> can use</p>",
        "id": 131178291,
        "sender_full_name": "Jake Goulding",
        "timestamp": 1533827352
    },
    {
        "content": "<p>We totally could, too. Maybe something to bring up.</p>",
        "id": 131178313,
        "sender_full_name": "simulacrum",
        "timestamp": 1533827400
    },
    {
        "content": "<p><a href=\"https://github.com/rust-lang/cargo/issues/3501\" target=\"_blank\" title=\"https://github.com/rust-lang/cargo/issues/3501\">https://github.com/rust-lang/cargo/issues/3501</a> ?</p>",
        "id": 131178547,
        "sender_full_name": "kennytm",
        "timestamp": 1533827619
    },
    {
        "content": "<p>And if someone adds the \"Run WASM\", that's a good distinction</p>",
        "id": 131179907,
        "sender_full_name": "Jake Goulding",
        "timestamp": 1533828857
    },
    {
        "content": "<p>“Show” has a bit of precedent in that the existing help text is already “build and show MIR”</p>",
        "id": 131181853,
        "sender_full_name": "lqd",
        "timestamp": 1533830709
    }
]