[
    {
        "content": "<p>I just published a crate to <a href=\"http://crates.io\">crates.io</a>. The doc build fails because one of the dependencies (<code>xcb</code>) apparently has a build script which tries to write into the read only filesystem (<code>OUT_DIR</code> not respected). Is there an easy way for me to avoid this? Removing the dependency is not an option.</p>",
        "id": 234208291,
        "sender_full_name": "Luis Wirth",
        "timestamp": 1618252429
    },
    {
        "content": "<p>Fix the build script to not do that would be my suggestion</p>",
        "id": 234209254,
        "sender_full_name": "Jonas Schievink  [he/him]",
        "timestamp": 1618252803
    },
    {
        "content": "<p><span class=\"user-mention\" data-user-id=\"311029\">@Luis Wirth</span> that should be fixed in the latest version of xcb IIRC</p>",
        "id": 234209697,
        "sender_full_name": "Joshua Nelson",
        "timestamp": 1618252988
    },
    {
        "content": "<p><span class=\"user-mention\" data-user-id=\"232545\">@Joshua Nelson</span> Thanks for letting me know :). I will switch from <code>clipboard</code> to <code>copypasta</code> because it has <code>xcb</code> up to date.</p>",
        "id": 234212203,
        "sender_full_name": "Luis Wirth",
        "timestamp": 1618254055
    }
]