[
    {
        "content": "<p>I'll be catching a flight so might not make tomorrow's meeting, should be fine though</p>",
        "id": 263103544,
        "sender_full_name": "Manish Goregaokar",
        "timestamp": 1638250230
    },
    {
        "content": "<p>Meeting <time datetime=\"2021-11-30T16:00:00Z\">2021-11-30T16:00:00Z</time> </p>\n<p>Agenda:</p>\n<ul>\n<li>Use new template forms for issue templates <a href=\"https://github.com/rust-lang/rust-clippy/issues/8032\">clippy#8032</a></li>\n<li>Missed sync + release</li>\n<li>...?</li>\n</ul>",
        "id": 263149400,
        "sender_full_name": "flip1995",
        "timestamp": 1638281367
    },
    {
        "content": "<p>Meeting in t-15 min</p>",
        "id": 263163373,
        "sender_full_name": "flip1995",
        "timestamp": 1638287159
    },
    {
        "content": "<p><span aria-label=\"wave\" class=\"emoji emoji-1f44b\" role=\"img\" title=\"wave\">:wave:</span></p>",
        "id": 263165809,
        "sender_full_name": "llogiq",
        "timestamp": 1638288132
    },
    {
        "content": "<p>I like the new template forms.</p>",
        "id": 263166157,
        "sender_full_name": "llogiq",
        "timestamp": 1638288252
    },
    {
        "content": "<p>Whoops, missed the start of the meeting</p>",
        "id": 263166471,
        "sender_full_name": "flip1995",
        "timestamp": 1638288367
    },
    {
        "content": "<p>Hey all <span aria-label=\"wave\" class=\"emoji emoji-1f44b\" role=\"img\" title=\"wave\">:wave:</span></p>",
        "id": 263166481,
        "sender_full_name": "flip1995",
        "timestamp": 1638288372
    },
    {
        "content": "<p>Yeah, I just wanted to bring the new template form to your attention.</p>",
        "id": 263166549,
        "sender_full_name": "flip1995",
        "timestamp": 1638288397
    },
    {
        "content": "<p>The main topic today is the missed sync last week and the release</p>",
        "id": 263166730,
        "sender_full_name": "flip1995",
        "timestamp": 1638288455
    },
    {
        "content": "<p>Whoa.</p>",
        "id": 263166753,
        "sender_full_name": "llogiq",
        "timestamp": 1638288463
    },
    {
        "content": "<p>The missed sync was a bit unlucky with RLS blocking us</p>",
        "id": 263167000,
        "sender_full_name": "flip1995",
        "timestamp": 1638288546
    },
    {
        "content": "<p>But I don't think we missed anything important for this release?</p>",
        "id": 263167051,
        "sender_full_name": "flip1995",
        "timestamp": 1638288571
    },
    {
        "content": "<p>ah so it was a bad combination of clippy-sync and no-tool-breakage week?</p>",
        "id": 263167116,
        "sender_full_name": "matthiaskrgr",
        "timestamp": 1638288599
    },
    {
        "content": "<p>Rather a unlucky situation where Clippy broke RLS, which almost never happens</p>",
        "id": 263167299,
        "sender_full_name": "flip1995",
        "timestamp": 1638288662
    },
    {
        "content": "<p>But this time right before a release in the no-tool-breakage week, yeah</p>",
        "id": 263167336,
        "sender_full_name": "flip1995",
        "timestamp": 1638288677
    },
    {
        "content": "<p>Igor said that they will return from their PTO in December, so we might get the sync in on time this Thursday</p>",
        "id": 263167499,
        "sender_full_name": "flip1995",
        "timestamp": 1638288738
    },
    {
        "content": "<p>But since it is release week, it's also CHANGELOG time. As always it would be really great if someone could write the CHANGELOG (doesn't have to be until Thursday)</p>",
        "id": 263167601,
        "sender_full_name": "flip1995",
        "timestamp": 1638288800
    },
    {
        "content": "<p>It should be shorter this time, because of the missed sync :D</p>",
        "id": 263167667,
        "sender_full_name": "flip1995",
        "timestamp": 1638288830
    },
    {
        "content": "<p>does it make sense for clippy folks to also get access to rls so they can merge \"fixes\" like this in case of emergencies?</p>",
        "id": 263167682,
        "sender_full_name": "matthiaskrgr",
        "timestamp": 1638288834
    },
    {
        "content": "<p>Not sure. I think the challenge here is, that Igor is the last remaining maintainer of RLS. So if they are on vacation or takes time off, it doesn't move forward</p>",
        "id": 263167899,
        "sender_full_name": "flip1995",
        "timestamp": 1638288907
    },
    {
        "content": "<p>I definitely DON'T want to blame Igor here !</p>",
        "id": 263167925,
        "sender_full_name": "flip1995",
        "timestamp": 1638288916
    },
    {
        "content": "<p>But that's it from me. Other topics you want to discuss <span class=\"user-mention\" data-user-id=\"261224\">@triagebot</span> end-meeting</p>",
        "id": 263168230,
        "sender_full_name": "flip1995",
        "timestamp": 1638289011
    },
    {
        "content": "<p>Does anyone have something to bring up?<br>\nReact with <span aria-label=\"working on it\" class=\"emoji emoji-1f6e0\" role=\"img\" title=\"working on it\">:working_on_it:</span> if you have something to say.<br>\nReact with <span aria-label=\"all good\" class=\"emoji emoji-2705\" role=\"img\" title=\"all good\">:all_good:</span> if you're ready to end the meeting.</p>",
        "id": 263168231,
        "sender_full_name": "triagebot",
        "timestamp": 1638289012
    },
    {
        "content": "<p>Have a good time, folks!</p>",
        "id": 263168312,
        "sender_full_name": "llogiq",
        "timestamp": 1638289048
    },
    {
        "content": "<p>Ok then, thanks for attending! <span aria-label=\"wave\" class=\"emoji emoji-1f44b\" role=\"img\" title=\"wave\">:wave:</span></p>",
        "id": 263168322,
        "sender_full_name": "flip1995",
        "timestamp": 1638289054
    }
]