[
    {
        "content": "<p>I am trying to fix <a href=\"https://github.com/rust-analyzer/rust-analyzer/issues/9904\">https://github.com/rust-analyzer/rust-analyzer/issues/9904</a> but I am unable to find trigger character set's definition. I have came across <a href=\"https://github.com/rust-analyzer/rust-analyzer/blob/b641a66078ce2f2363e9a3b050ba448b93fb7cb6/crates/ide_completion/src/render/macro_.rs#L57\">this block</a> which handles the bang case. Should it be extended to handle <code>!needs_bang</code> as well? Am I on the right track?</p>",
        "id": 249549836,
        "sender_full_name": "Manas",
        "timestamp": 1629090789
    },
    {
        "content": "<p>There's <code>TRIGGER_CHARS</code> in <code>typing.rs</code>, but I'm not sure it helps there.</p>",
        "id": 249550196,
        "sender_full_name": "Laurențiu",
        "timestamp": 1629091228
    },
    {
        "content": "<p>I went through it. It seems like it doesn't. Perhaps, the fix is not just the missing of <code>!</code> in trigger char set.</p>",
        "id": 249551161,
        "sender_full_name": "Manas",
        "timestamp": 1629092435
    },
    {
        "content": "<p><a href=\"https://github.com/rust-analyzer/rust-analyzer/blob/068ede0991ae79f2ffcfd83fb70e40af1eee12ef/crates/rust-analyzer/src/caps.rs#L31\">https://github.com/rust-analyzer/rust-analyzer/blob/068ede0991ae79f2ffcfd83fb70e40af1eee12ef/crates/rust-analyzer/src/caps.rs#L31</a></p>",
        "id": 249555867,
        "sender_full_name": "Lukas Wirth",
        "timestamp": 1629097634
    },
    {
        "content": "<p>This is the place I was referring to</p>",
        "id": 249555871,
        "sender_full_name": "Lukas Wirth",
        "timestamp": 1629097640
    },
    {
        "content": "<p>but I might be wrong</p>",
        "id": 249555874,
        "sender_full_name": "Lukas Wirth",
        "timestamp": 1629097642
    }
]