[
    {
        "content": "<p>While thinking about expressions at work last night (instead of working... :P) I had the realization that temporaries and possibly move/copy are more about places themselves than about expressions. Would it make sense to have a chapter called \"Places\" in the memory model section that describes these alongside what actual kinds of places there are (local variables, statics, temporaries, (etc?))?</p>",
        "id": 233238739,
        "sender_full_name": "isHavvy",
        "timestamp": 1617660841
    },
    {
        "content": "<p>Like, as a hastily thought out outline:</p>\n<div class=\"codehilite\" data-code-language=\"markdown\"><pre><span></span><code><span class=\"gh\"># Places</span>\n<span class=\"gu\">## General definition</span>\n<span class=\"gu\">## Kinds of Places</span>\n<span class=\"gu\">### Statics</span>\n<span class=\"gu\">### Local Variables</span>\n<span class=\"gu\">### Temporaries</span>\n<span class=\"gu\">## Reading</span>\n<span class=\"gu\">### Moving/Copying</span>\n<span class=\"gu\">## Writing</span>\n<span class=\"gu\">### Mutability</span>\n<span class=\"gu\">### Drop?</span>\n</code></pre></div>",
        "id": 233245186,
        "sender_full_name": "isHavvy",
        "timestamp": 1617665418
    },
    {
        "content": "<p>this is good.</p>",
        "id": 233247493,
        "sender_full_name": "Lokathor",
        "timestamp": 1617667113
    }
]