[
    {
        "content": "<p>Hey, in the spirit of Niko's \"shiny future\" work, I thought I'd write up something as a thought experiment: <a href=\"https://carllerche.com/2021/06/17/six-ways-to-make-async-rust-easier/\">https://carllerche.com/2021/06/17/six-ways-to-make-async-rust-easier/</a></p>",
        "id": 243063536,
        "sender_full_name": "Carl Lerche",
        "timestamp": 1623954951
    },
    {
        "content": "<p>Love it! Definitely goes a long way to link all the problems and proposals together, and is hopefully accessible to more people than the \"asynce experts\". Happy to see all the references.</p>",
        "id": 243124824,
        "sender_full_name": "Matthias247",
        "timestamp": 1624001136
    },
    {
        "content": "<p><span class=\"user-mention silent\" data-user-id=\"224941\">Carl Lerche</span> <a href=\"#narrow/stream/187312-wg-async-foundations/topic/a-shiny-future/near/243063536\">said</a>:</p>\n<blockquote>\n<p>Hey, in the spirit of Niko's \"shiny future\" work, I thought I'd write up something as a thought experiment: <a href=\"https://carllerche.com/2021/06/17/six-ways-to-make-async-rust-easier/\">https://carllerche.com/2021/06/17/six-ways-to-make-async-rust-easier/</a></p>\n</blockquote>\n<p>It is really nice and helpful</p>\n<p>Thanks carl.</p>",
        "id": 243126207,
        "sender_full_name": "Nathaniel Bajo",
        "timestamp": 1624002266
    }
]