[
    {
        "content": "<p>I opened <a href=\"https://github.com/rust-lang/wg-async-foundations/pull/109\">https://github.com/rust-lang/wg-async-foundations/pull/109</a> but i realized the tests probably won't pass. I need to go to bed. If anybody wants to take a stab at fixing up SUMMARY.md and making the tests pass, it'd be appreciated. (You have to add <code>ignore</code> to the code snippets)</p>",
        "id": 232524002,
        "sender_full_name": "nikomatsakis",
        "timestamp": 1617155259
    },
    {
        "content": "<p>i can work on this later today (in about ~4 hours from now, or sooner)</p>",
        "id": 232608487,
        "sender_full_name": "Andrew Chin (eminence)",
        "timestamp": 1617203541
    },
    {
        "content": "<p>ok, you got lucky.  i happened to be in a boring meeting, which means i had a few minutes <span aria-label=\"laughter tears\" class=\"emoji emoji-1f602\" role=\"img\" title=\"laughter tears\">:laughter_tears:</span>   <a href=\"https://github.com/rust-lang/wg-async-foundations/issues/110\">wg-async-foundations#110</a></p>",
        "id": 232614509,
        "sender_full_name": "Andrew Chin (eminence)",
        "timestamp": 1617205574
    }
]